[
  {
    "CountryId": 1,
    "CountryName": "France",
    "Cities": [
      {
        "CityId": 1,
        "CityName": "Paris"
      },
      {
        "CityId": 4,
        "CityName": "Lyon"
      }
    ]
  },
  {
    "CountryId": 2,
    "CountryName": "United Kingdom",
    "Cities": [
      {
        "CityId": 2,
        "CityName": "London"
      }
    ]
  },
  {
    "CountryId": 3,
    "CountryName": "Germany",
    "Cities": [
      {
        "CityId": 3,
        "CityName": "Berlin"
      }
    ]
  }
]
